{
  "hash": "1778092e1739155acec35a3bccee2fb8a1ae4e91",
  "hash_short": "1778092e",
  "subject": "nl80211: Require auth type for NL80211_CMD_AUTHENTICATE",
  "body": "NL80211_ATTR_AUTH_TYPE is a required parameter for\nNL80211_CMD_AUTHENTICATE. We are currently (by chance) defaulting to\nopen system authentication if the attribute is not specified. It is\nbetter to just reject the invalid command.\n\nSigned-off-by: Jouni Malinen <j@w1.fi>\nSigned-off-by: John W. Linville <linville@tuxdriver.com>",
  "full_message": "nl80211: Require auth type for NL80211_CMD_AUTHENTICATE\n\nNL80211_ATTR_AUTH_TYPE is a required parameter for\nNL80211_CMD_AUTHENTICATE. We are currently (by chance) defaulting to\nopen system authentication if the attribute is not specified. It is\nbetter to just reject the invalid command.\n\nSigned-off-by: Jouni Malinen <j@w1.fi>\nSigned-off-by: John W. Linville <linville@tuxdriver.com>",
  "author_name": "Jouni Malinen",
  "author_email": "j@w1.fi",
  "author_date": "Fri Mar 27 20:52:47 2009 +0200",
  "author_date_iso": "2009-03-27T20:52:47+02:00",
  "committer_name": "John W. Linville",
  "committer_email": "linville@tuxdriver.com",
  "committer_date": "Wed Apr 22 16:54:28 2009 -0400",
  "committer_date_iso": "2009-04-22T16:54:28-04:00",
  "files_changed": [
    "net/wireless/nl80211.c"
  ],
  "files_changed_count": 1,
  "stats": [
    {
      "file": "net/wireless/nl80211.c",
      "insertions": 7,
      "deletions": 7
    }
  ],
  "total_insertions": 7,
  "total_deletions": 7,
  "total_changes": 14,
  "parents": [
    "c0ed418977edf60f1df9933e1ccd48920a28eb66"
  ],
  "branches": [
    "* development",
    "master",
    "remotes/origin/HEAD -> origin/master",
    "remotes/origin/master"
  ],
  "tags": [
    "v2.6.31",
    "v2.6.31-rc1",
    "v2.6.31-rc2",
    "v2.6.31-rc3",
    "v2.6.31-rc4",
    "v2.6.31-rc5",
    "v2.6.31-rc6",
    "v2.6.31-rc7",
    "v2.6.31-rc8",
    "v2.6.31-rc9"
  ],
  "is_merge": false,
  "security_info": {
    "cve_ids": [],
    "security_keywords": [
      "auth"
    ]
  },
  "fix_type": "security",
  "file_results": [
    {
      "file": "net/wireless/nl80211.c",
      "pre_version": false,
      "post_version": true,
      "patch": true
    }
  ]
}