{
  "hash": "4c91307ce9387519836e17482906ef0f698ea7d9",
  "hash_short": "4c91307c",
  "subject": "i2c: uniphier: avoid WARN_ON() of clk_disable() in failure path",
  "body": "If clk_prepare_enable() fails, clk_disable_unprepare() is called in\nthe failure path, where the enable_count is still zero, so it hits\nWARN_ON(core->enable_count == 0) in the clk_core_disable().\n\nTo fix this, make the clock setting more linear in the probe function\nso that it can exploit \"goto err\" in case of error.\n\nSigned-off-by: Masahiro Yamada <yamada.masahiro@socionext.com>\nSigned-off-by: Wolfram Sang <wsa@the-dreams.de>",
  "full_message": "i2c: uniphier: avoid WARN_ON() of clk_disable() in failure path\n\nIf clk_prepare_enable() fails, clk_disable_unprepare() is called in\nthe failure path, where the enable_count is still zero, so it hits\nWARN_ON(core->enable_count == 0) in the clk_core_disable().\n\nTo fix this, make the clock setting more linear in the probe function\nso that it can exploit \"goto err\" in case of error.\n\nSigned-off-by: Masahiro Yamada <yamada.masahiro@socionext.com>\nSigned-off-by: Wolfram Sang <wsa@the-dreams.de>",
  "author_name": "Masahiro Yamada",
  "author_email": "yamada.masahiro@socionext.com",
  "author_date": "Thu Sep 1 20:46:28 2016 +0900",
  "author_date_iso": "2016-09-01T20:46:28+09:00",
  "committer_name": "Wolfram Sang",
  "committer_email": "wsa@the-dreams.de",
  "committer_date": "Thu Sep 8 22:40:32 2016 +0200",
  "committer_date_iso": "2016-09-08T22:40:32+02:00",
  "files_changed": [
    "drivers/i2c/busses/i2c-uniphier.c"
  ],
  "files_changed_count": 1,
  "stats": [
    {
      "file": "drivers/i2c/busses/i2c-uniphier.c",
      "insertions": 31,
      "deletions": 42
    }
  ],
  "total_insertions": 31,
  "total_deletions": 42,
  "total_changes": 73,
  "parents": [
    "fbf8090b723d4df3cfe18c9491a8bc21ec15a5c0"
  ],
  "branches": [
    "* development",
    "master",
    "remotes/origin/HEAD -> origin/master",
    "remotes/origin/master"
  ],
  "tags": [
    "v4.10",
    "v4.10-rc1",
    "v4.10-rc2",
    "v4.10-rc3",
    "v4.10-rc4",
    "v4.10-rc5",
    "v4.10-rc6",
    "v4.10-rc7",
    "v4.10-rc8",
    "v4.11"
  ],
  "is_merge": false,
  "security_info": {
    "cve_ids": [],
    "security_keywords": [
      "exploit"
    ]
  },
  "fix_type": "security",
  "file_results": [
    {
      "file": "drivers/i2c/busses/i2c-uniphier.c",
      "pre_version": false,
      "post_version": true,
      "patch": true
    }
  ]
}