{
  "hash": "90f192c8241e431d2c3076e4f2cb99ac25bfb1c5",
  "hash_short": "90f192c8",
  "subject": "drm/i915/GuC/GLK: Load GuC on GLK",
  "body": "Load GuC 10.56 on GLK. Work on firmware is still\nin progress. Testing has not been done yet.\nThis patch addresses the initial need to load the GuC\nfirmware for HuC authentication\n\nv2: rebased.\n\nCc: Jeff mcgee <jeff.mcgee@intel.com>\nCc: Rodrigo Vivi <rodrigo.vivi@intel.com>\nCc: John Spotswood <john.a.spotswood@intel.com>\nSigned-off-by: Anusha Srivatsa <anusha.srivatsa@intel.com>\nReviewed-by: John Spotswood <john.a.spotswood@intel.com>\nSigned-off-by: Ander Conselvan de Oliveira <ander.conselvan.de.oliveira@intel.com>\nLink: http://patchwork.freedesktop.org/patch/msgid/1490905447-15815-1-git-send-email-anusha.srivatsa@intel.com",
  "full_message": "drm/i915/GuC/GLK: Load GuC on GLK\n\nLoad GuC 10.56 on GLK. Work on firmware is still\nin progress. Testing has not been done yet.\nThis patch addresses the initial need to load the GuC\nfirmware for HuC authentication\n\nv2: rebased.\n\nCc: Jeff mcgee <jeff.mcgee@intel.com>\nCc: Rodrigo Vivi <rodrigo.vivi@intel.com>\nCc: John Spotswood <john.a.spotswood@intel.com>\nSigned-off-by: Anusha Srivatsa <anusha.srivatsa@intel.com>\nReviewed-by: John Spotswood <john.a.spotswood@intel.com>\nSigned-off-by: Ander Conselvan de Oliveira <ander.conselvan.de.oliveira@intel.com>\nLink: http://patchwork.freedesktop.org/patch/msgid/1490905447-15815-1-git-send-email-anusha.srivatsa@intel.com",
  "author_name": "Anusha Srivatsa",
  "author_email": "anusha.srivatsa@intel.com",
  "author_date": "Thu Mar 30 13:24:06 2017 -0700",
  "author_date_iso": "2017-03-30T13:24:06-07:00",
  "committer_name": "Ander Conselvan de Oliveira",
  "committer_email": "ander.conselvan.de.oliveira@intel.com",
  "committer_date": "Fri Apr 7 10:23:19 2017 +0300",
  "committer_date_iso": "2017-04-07T10:23:19+03:00",
  "files_changed": [
    "drivers/gpu/drm/i915/intel_guc_loader.c"
  ],
  "files_changed_count": 1,
  "stats": [
    {
      "file": "drivers/gpu/drm/i915/intel_guc_loader.c",
      "insertions": 9,
      "deletions": 0
    }
  ],
  "total_insertions": 9,
  "total_deletions": 0,
  "total_changes": 9,
  "parents": [
    "b268d9fe0f10544f5f7a1b7015e2b97075e6215d"
  ],
  "branches": [
    "* development",
    "master",
    "remotes/origin/HEAD -> origin/master",
    "remotes/origin/master"
  ],
  "tags": [
    "v4.13",
    "v4.13-rc1",
    "v4.13-rc2",
    "v4.13-rc3",
    "v4.13-rc4",
    "v4.13-rc5",
    "v4.13-rc6",
    "v4.13-rc7",
    "v4.14",
    "v4.14-rc1"
  ],
  "is_merge": false,
  "security_info": {
    "cve_ids": [],
    "security_keywords": [
      "authentication"
    ]
  },
  "fix_type": "security",
  "file_results": [
    {
      "file": "drivers/gpu/drm/i915/intel_guc_loader.c",
      "pre_version": false,
      "post_version": true,
      "patch": true
    }
  ]
}