{
  "hash": "40294d8f14384780a61a2dea8c92a231176ae301",
  "hash_short": "40294d8f",
  "subject": "PCI: Fix uninitialized variable bug in AER injection code",
  "body": "If it was preempted, and the variable aer_mask_override is changed\nafter the spin_unlock_irqrestore it will write an uninitialized\nvariable by the pci_write_config_dword() function.\n\nSigned-off-by: Wanlong Gao <wanlong.gao@gmail.com>\nSigned-off-by: Jesse Barnes <jbarnes@virtuousgeek.org>",
  "full_message": "PCI: Fix uninitialized variable bug in AER injection code\n\nIf it was preempted, and the variable aer_mask_override is changed\nafter the spin_unlock_irqrestore it will write an uninitialized\nvariable by the pci_write_config_dword() function.\n\nSigned-off-by: Wanlong Gao <wanlong.gao@gmail.com>\nSigned-off-by: Jesse Barnes <jbarnes@virtuousgeek.org>",
  "author_name": "Wanlong Gao",
  "author_email": "wanlong.gao@gmail.com",
  "author_date": "Mon Apr 4 17:12:59 2011 +0800",
  "author_date_iso": "2011-04-04T17:12:59+08:00",
  "committer_name": "Jesse Barnes",
  "committer_email": "jbarnes@virtuousgeek.org",
  "committer_date": "Tue May 10 15:43:30 2011 -0700",
  "committer_date_iso": "2011-05-10T15:43:30-07:00",
  "files_changed": [
    "drivers/pci/pcie/aer/aer_inject.c"
  ],
  "files_changed_count": 1,
  "stats": [
    {
      "file": "drivers/pci/pcie/aer/aer_inject.c",
      "insertions": 1,
      "deletions": 1
    }
  ],
  "total_insertions": 1,
  "total_deletions": 1,
  "total_changes": 2,
  "parents": [
    "0e8ede5351b53610363215f750e576ca1db1d0cd"
  ],
  "branches": [
    "* development",
    "master",
    "remotes/origin/HEAD -> origin/master",
    "remotes/origin/master"
  ],
  "tags": [
    "v3.0",
    "v3.0-rc1",
    "v3.0-rc2",
    "v3.0-rc3",
    "v3.0-rc4",
    "v3.0-rc5",
    "v3.0-rc6",
    "v3.0-rc7",
    "v3.1",
    "v3.1-rc1"
  ],
  "is_merge": false,
  "security_info": {
    "cve_ids": [],
    "security_keywords": [
      "injection"
    ]
  },
  "fix_type": "security",
  "file_results": [
    {
      "file": "drivers/pci/pcie/aer/aer_inject.c",
      "pre_version": false,
      "post_version": true,
      "patch": true
    }
  ]
}