{
  "hash": "324105775c1982aacbd2972b7024d8cc06474abe",
  "hash_short": "32410577",
  "subject": "f2fs: support fault injection for f2fs_kmem_cache_alloc()",
  "body": "This patch supports to inject fault into f2fs_kmem_cache_alloc().\n\nUsage:\na) echo 32768 > /sys/fs/f2fs/<dev>/inject_type or\nb) mount -o fault_type=32768 <dev> <mountpoint>\n\nSigned-off-by: Chao Yu <chao@kernel.org>\nSigned-off-by: Jaegeuk Kim <jaegeuk@kernel.org>",
  "full_message": "f2fs: support fault injection for f2fs_kmem_cache_alloc()\n\nThis patch supports to inject fault into f2fs_kmem_cache_alloc().\n\nUsage:\na) echo 32768 > /sys/fs/f2fs/<dev>/inject_type or\nb) mount -o fault_type=32768 <dev> <mountpoint>\n\nSigned-off-by: Chao Yu <chao@kernel.org>\nSigned-off-by: Jaegeuk Kim <jaegeuk@kernel.org>",
  "author_name": "Chao Yu",
  "author_email": "chao@kernel.org",
  "author_date": "Mon Aug 9 08:24:48 2021 +0800",
  "author_date_iso": "2021-08-09T08:24:48+08:00",
  "committer_name": "Jaegeuk Kim",
  "committer_email": "jaegeuk@kernel.org",
  "committer_date": "Tue Aug 17 11:59:05 2021 -0700",
  "committer_date_iso": "2021-08-17T11:59:05-07:00",
  "files_changed": [
    "Documentation/filesystems/f2fs.rst",
    "fs/f2fs/checkpoint.c",
    "fs/f2fs/compress.c",
    "fs/f2fs/data.c",
    "fs/f2fs/dir.c",
    "fs/f2fs/extent_cache.c",
    "fs/f2fs/f2fs.h",
    "fs/f2fs/gc.c",
    "fs/f2fs/node.c",
    "fs/f2fs/recovery.c",
    "fs/f2fs/segment.c",
    "fs/f2fs/super.c",
    "fs/f2fs/xattr.c"
  ],
  "files_changed_count": 13,
  "stats": [
    {
      "file": "Documentation/filesystems/f2fs.rst",
      "insertions": 1,
      "deletions": 0
    },
    {
      "file": "fs/f2fs/checkpoint.c",
      "insertions": 2,
      "deletions": 1
    },
    {
      "file": "fs/f2fs/compress.c",
      "insertions": 5,
      "deletions": 3
    },
    {
      "file": "fs/f2fs/data.c",
      "insertions": 1,
      "deletions": 1
    },
    {
      "file": "fs/f2fs/dir.c",
      "insertions": 2,
      "deletions": 2
    },
    {
      "file": "fs/f2fs/extent_cache.c",
      "insertions": 3,
      "deletions": 2
    },
    {
      "file": "fs/f2fs/f2fs.h",
      "insertions": 16,
      "deletions": 1
    },
    {
      "file": "fs/f2fs/gc.c",
      "insertions": 4,
      "deletions": 2
    },
    {
      "file": "fs/f2fs/node.c",
      "insertions": 12,
      "deletions": 11
    },
    {
      "file": "fs/f2fs/recovery.c",
      "insertions": 2,
      "deletions": 1
    },
    {
      "file": "fs/f2fs/segment.c",
      "insertions": 6,
      "deletions": 4
    },
    {
      "file": "fs/f2fs/super.c",
      "insertions": 3,
      "deletions": 1
    },
    {
      "file": "fs/f2fs/xattr.c",
      "insertions": 2,
      "deletions": 1
    }
  ],
  "total_insertions": 59,
  "total_deletions": 30,
  "total_changes": 89,
  "parents": [
    "4a4fc043f594d39edc976a3a3dce7c40ebb86f3f"
  ],
  "branches": [
    "* development",
    "remotes/origin/HEAD -> origin/master",
    "remotes/origin/master"
  ],
  "tags": [],
  "is_merge": false,
  "security_info": {
    "cve_ids": [],
    "security_keywords": [
      "injection"
    ]
  },
  "fix_type": "security",
  "file_results": [
    {
      "file": "fs/f2fs/checkpoint.c",
      "pre_version": false,
      "post_version": true,
      "patch": true
    },
    {
      "file": "fs/f2fs/compress.c",
      "pre_version": false,
      "post_version": true,
      "patch": true
    },
    {
      "file": "Documentation/filesystems/f2fs.rst",
      "pre_version": true,
      "post_version": true,
      "patch": true
    },
    {
      "file": "fs/f2fs/extent_cache.c",
      "pre_version": false,
      "post_version": true,
      "patch": true
    },
    {
      "file": "fs/f2fs/gc.c",
      "pre_version": false,
      "post_version": true,
      "patch": true
    },
    {
      "file": "fs/f2fs/node.c",
      "pre_version": false,
      "post_version": true,
      "patch": true
    },
    {
      "file": "fs/f2fs/dir.c",
      "pre_version": false,
      "post_version": true,
      "patch": true
    },
    {
      "file": "fs/f2fs/data.c",
      "pre_version": false,
      "post_version": true,
      "patch": true
    },
    {
      "file": "fs/f2fs/f2fs.h",
      "pre_version": false,
      "post_version": true,
      "patch": true
    },
    {
      "file": "fs/f2fs/recovery.c",
      "pre_version": false,
      "post_version": true,
      "patch": true
    },
    {
      "file": "fs/f2fs/segment.c",
      "pre_version": false,
      "post_version": true,
      "patch": true
    },
    {
      "file": "fs/f2fs/xattr.c",
      "pre_version": false,
      "post_version": true,
      "patch": true
    },
    {
      "file": "fs/f2fs/super.c",
      "pre_version": false,
      "post_version": true,
      "patch": true
    }
  ]
}