{
  "hash": "1ad32105d78e4b5da60688eca014bcd45271318f",
  "hash_short": "1ad32105",
  "subject": "KVM: x86: selftests: test simultaneous uses of V_IRQ from L1 and L0",
  "body": "Test that if:\n\n* L1 disables virtual interrupt masking, and INTR intercept.\n\n* L1 setups a virtual interrupt to be injected to L2 and enters L2 with\n  interrupts disabled, thus the virtual interrupt is pending.\n\n* Now an external interrupt arrives in L1 and since\n  L1 doesn't intercept it, it should be delivered to L2 when\n  it enables interrupts.\n\n  to do this L0 (abuses) V_IRQ to setup an\n  interrupt window, and returns to L2.\n\n* L2 enables interrupts.\n  This should trigger the interrupt window,\n  injection of the external interrupt and delivery\n  of the virtual interrupt that can now be done.\n\n* Test that now L2 gets those interrupts.\n\nThis is the test that demonstrates the issue that was\nfixed in the previous patch.\n\nSigned-off-by: Maxim Levitsky <mlevitsk@redhat.com>\nMessage-Id: <20210914154825.104886-3-mlevitsk@redhat.com>\nSigned-off-by: Paolo Bonzini <pbonzini@redhat.com>",
  "full_message": "KVM: x86: selftests: test simultaneous uses of V_IRQ from L1 and L0\n\nTest that if:\n\n* L1 disables virtual interrupt masking, and INTR intercept.\n\n* L1 setups a virtual interrupt to be injected to L2 and enters L2 with\n  interrupts disabled, thus the virtual interrupt is pending.\n\n* Now an external interrupt arrives in L1 and since\n  L1 doesn't intercept it, it should be delivered to L2 when\n  it enables interrupts.\n\n  to do this L0 (abuses) V_IRQ to setup an\n  interrupt window, and returns to L2.\n\n* L2 enables interrupts.\n  This should trigger the interrupt window,\n  injection of the external interrupt and delivery\n  of the virtual interrupt that can now be done.\n\n* Test that now L2 gets those interrupts.\n\nThis is the test that demonstrates the issue that was\nfixed in the previous patch.\n\nSigned-off-by: Maxim Levitsky <mlevitsk@redhat.com>\nMessage-Id: <20210914154825.104886-3-mlevitsk@redhat.com>\nSigned-off-by: Paolo Bonzini <pbonzini@redhat.com>",
  "author_name": "Maxim Levitsky",
  "author_email": "mlevitsk@redhat.com",
  "author_date": "Tue Sep 14 18:48:13 2021 +0300",
  "author_date_iso": "2021-09-14T18:48:13+03:00",
  "committer_name": "Paolo Bonzini",
  "committer_email": "pbonzini@redhat.com",
  "committer_date": "Thu Sep 23 10:05:07 2021 -0400",
  "committer_date_iso": "2021-09-23T10:05:07-04:00",
  "files_changed": [
    "tools/testing/selftests/kvm/.gitignore",
    "tools/testing/selftests/kvm/Makefile",
    "tools/testing/selftests/kvm/x86_64/svm_int_ctl_test.c"
  ],
  "files_changed_count": 3,
  "stats": [
    {
      "file": "tools/testing/selftests/kvm/.gitignore",
      "insertions": 1,
      "deletions": 0
    },
    {
      "file": "tools/testing/selftests/kvm/Makefile",
      "insertions": 1,
      "deletions": 0
    },
    {
      "file": "tools/testing/selftests/kvm/x86_64/svm_int_ctl_test.c",
      "insertions": 128,
      "deletions": 0
    }
  ],
  "total_insertions": 130,
  "total_deletions": 0,
  "total_changes": 130,
  "parents": [
    "aee77e1169c1900fe4248dc186962e745b479d9e"
  ],
  "branches": [
    "* development",
    "remotes/origin/HEAD -> origin/master",
    "remotes/origin/master"
  ],
  "tags": [],
  "is_merge": false,
  "security_info": {
    "cve_ids": [],
    "security_keywords": [
      "injection"
    ]
  },
  "fix_type": "security",
  "file_results": [
    {
      "file": "tools/testing/selftests/kvm/.gitignore",
      "pre_version": false,
      "post_version": true,
      "patch": true
    },
    {
      "file": "tools/testing/selftests/kvm/Makefile",
      "pre_version": false,
      "post_version": true,
      "patch": true
    },
    {
      "file": "tools/testing/selftests/kvm/x86_64/svm_int_ctl_test.c",
      "pre_version": false,
      "post_version": true,
      "patch": true
    }
  ]
}