{
  "hash": "d1dbab52ebc2447c7aa623b8d677135a6b23e406",
  "hash_short": "d1dbab52",
  "subject": "KVM: s390: selftests: Add regression tests for KMAC, KMC, KM, KIMD and KLMD crypto subfunctions",
  "body": "Extend the existing regression test framework for s390x CPU subfunctions\nto include tests for the KMAC (Compute Message Authentication Code),\nKMC (Cipher Message with Chaining), KM (Cipher Message) KIMD (Compute\nIntermediate Message Digest) and KLMD (Compute Last Message Digest)\ncrypto functions.\n\nThe test procedure follows the established pattern.\n\nSuggested-by: Janosch Frank <frankja@linux.ibm.com>\nSigned-off-by: Hariharan Mari <hari55@linux.ibm.com>\nReviewed-by: Janosch Frank <frankja@linux.ibm.com>\nReviewed-by: Christoph Schlameuss <schlameuss@linux.ibm.com>\nLink: https://lore.kernel.org/r/20240823130947.38323-5-hari55@linux.ibm.com\nSigned-off-by: Janosch Frank <frankja@linux.ibm.com>\nMessage-ID: <20240823130947.38323-5-hari55@linux.ibm.com>",
  "full_message": "KVM: s390: selftests: Add regression tests for KMAC, KMC, KM, KIMD and KLMD crypto subfunctions\n\nExtend the existing regression test framework for s390x CPU subfunctions\nto include tests for the KMAC (Compute Message Authentication Code),\nKMC (Cipher Message with Chaining), KM (Cipher Message) KIMD (Compute\nIntermediate Message Digest) and KLMD (Compute Last Message Digest)\ncrypto functions.\n\nThe test procedure follows the established pattern.\n\nSuggested-by: Janosch Frank <frankja@linux.ibm.com>\nSigned-off-by: Hariharan Mari <hari55@linux.ibm.com>\nReviewed-by: Janosch Frank <frankja@linux.ibm.com>\nReviewed-by: Christoph Schlameuss <schlameuss@linux.ibm.com>\nLink: https://lore.kernel.org/r/20240823130947.38323-5-hari55@linux.ibm.com\nSigned-off-by: Janosch Frank <frankja@linux.ibm.com>\nMessage-ID: <20240823130947.38323-5-hari55@linux.ibm.com>",
  "author_name": "Hariharan Mari",
  "author_email": "hari55@linux.ibm.com",
  "author_date": "Fri Aug 23 15:05:07 2024 +0200",
  "author_date_iso": "2024-08-23T15:05:07+02:00",
  "committer_name": "Janosch Frank",
  "committer_email": "frankja@linux.ibm.com",
  "committer_date": "Mon Oct 7 08:53:55 2024 +0000",
  "committer_date_iso": "2024-10-07T08:53:55+00:00",
  "files_changed": [
    "tools/testing/selftests/kvm/s390x/cpumodel_subfuncs_test.c"
  ],
  "files_changed_count": 1,
  "stats": [
    {
      "file": "tools/testing/selftests/kvm/s390x/cpumodel_subfuncs_test.c",
      "insertions": 61,
      "deletions": 0
    }
  ],
  "total_insertions": 61,
  "total_deletions": 0,
  "total_changes": 61,
  "parents": [
    "7f269dd22d51fc21c4a2a561cb93652c29f9863c"
  ],
  "branches": [
    "* development",
    "remotes/origin/HEAD -> origin/master",
    "remotes/origin/master"
  ],
  "tags": [],
  "is_merge": false,
  "security_info": {
    "cve_ids": [],
    "security_keywords": [
      "Authentication"
    ]
  },
  "fix_type": "security",
  "file_results": [
    {
      "file": "tools/testing/selftests/kvm/s390x/cpumodel_subfuncs_test.c",
      "pre_version": true,
      "post_version": true,
      "patch": true
    }
  ]
}