{
  "hash": "44b372d8a099a7042f9f17ebd4941050e38c1773",
  "hash_short": "44b372d8",
  "subject": "powerpc/vio: Separate vio bus probe and device probe",
  "body": "Similar to PCI, separate the bus probe from device probe. This allows\nus to attach bus notifiers for DMA debug and IOMMU fault injection\nbefore devices have been probed.\n\nSigned-off-by: Anton Blanchard <anton@samba.org>\nSigned-off-by: Benjamin Herrenschmidt <benh@kernel.crashing.org>",
  "full_message": "powerpc/vio: Separate vio bus probe and device probe\n\nSimilar to PCI, separate the bus probe from device probe. This allows\nus to attach bus notifiers for DMA debug and IOMMU fault injection\nbefore devices have been probed.\n\nSigned-off-by: Anton Blanchard <anton@samba.org>\nSigned-off-by: Benjamin Herrenschmidt <benh@kernel.crashing.org>",
  "author_name": "Anton Blanchard",
  "author_email": "anton@samba.org",
  "author_date": "Sun Jun 24 18:24:44 2012 +0000",
  "author_date_iso": "2012-06-24T18:24:44+00:00",
  "committer_name": "Benjamin Herrenschmidt",
  "committer_email": "benh@kernel.crashing.org",
  "committer_date": "Tue Jul 10 19:18:54 2012 +1000",
  "committer_date_iso": "2012-07-10T19:18:54+10:00",
  "files_changed": [
    "arch/powerpc/kernel/vio.c"
  ],
  "files_changed_count": 1,
  "stats": [
    {
      "file": "arch/powerpc/kernel/vio.c",
      "insertions": 7,
      "deletions": 1
    }
  ],
  "total_insertions": 7,
  "total_deletions": 1,
  "total_changes": 8,
  "parents": [
    "62761d1f68937b4d3dd509032942290f2359bde7"
  ],
  "branches": [
    "* development",
    "master",
    "remotes/origin/HEAD -> origin/master",
    "remotes/origin/master"
  ],
  "tags": [
    "v3.10",
    "v3.10-rc1",
    "v3.10-rc2",
    "v3.10-rc3",
    "v3.10-rc4",
    "v3.10-rc5",
    "v3.10-rc6",
    "v3.10-rc7",
    "v3.11",
    "v3.11-rc1"
  ],
  "is_merge": false,
  "security_info": {
    "cve_ids": [],
    "security_keywords": [
      "injection"
    ]
  },
  "fix_type": "security",
  "file_results": [
    {
      "file": "arch/powerpc/kernel/vio.c",
      "pre_version": true,
      "post_version": true,
      "patch": true
    }
  ]
}