{
  "hash": "0c36211bac9b03de2e010597303b930211068caa",
  "hash_short": "0c36211b",
  "subject": "bnxt_en: Add RSS support for IPSEC headers",
  "body": "IPSec uses two distinct protocols, Authentication Header (AH) and\nEncapsulating Security Payload (ESP).\nAdd support to configure RSS based on AH and ESP headers.\nThis functionality will be enabled based on the capabilities\nindicated by the firmware in HWRM_VNIC_QCAPS.\n\nSigned-off-by: Ajit Khaparde <ajit.khaparde@broadcom.com>\nSigned-off-by: Michael Chan <michael.chan@broadcom.com>\nLink: https://lore.kernel.org/r/20240205223202.25341-14-michael.chan@broadcom.com\nSigned-off-by: Jakub Kicinski <kuba@kernel.org>",
  "full_message": "bnxt_en: Add RSS support for IPSEC headers\n\nIPSec uses two distinct protocols, Authentication Header (AH) and\nEncapsulating Security Payload (ESP).\nAdd support to configure RSS based on AH and ESP headers.\nThis functionality will be enabled based on the capabilities\nindicated by the firmware in HWRM_VNIC_QCAPS.\n\nSigned-off-by: Ajit Khaparde <ajit.khaparde@broadcom.com>\nSigned-off-by: Michael Chan <michael.chan@broadcom.com>\nLink: https://lore.kernel.org/r/20240205223202.25341-14-michael.chan@broadcom.com\nSigned-off-by: Jakub Kicinski <kuba@kernel.org>",
  "author_name": "Ajit Khaparde",
  "author_email": "ajit.khaparde@broadcom.com",
  "author_date": "Mon Feb 5 14:32:02 2024 -0800",
  "author_date_iso": "2024-02-05T14:32:02-08:00",
  "committer_name": "Jakub Kicinski",
  "committer_email": "kuba@kernel.org",
  "committer_date": "Fri Feb 9 12:37:42 2024 -0800",
  "committer_date_iso": "2024-02-09T12:37:42-08:00",
  "files_changed": [
    "drivers/net/ethernet/broadcom/bnxt/bnxt.c",
    "drivers/net/ethernet/broadcom/bnxt/bnxt.h",
    "drivers/net/ethernet/broadcom/bnxt/bnxt_ethtool.c"
  ],
  "files_changed_count": 3,
  "stats": [
    {
      "file": "drivers/net/ethernet/broadcom/bnxt/bnxt.c",
      "insertions": 13,
      "deletions": 2
    },
    {
      "file": "drivers/net/ethernet/broadcom/bnxt/bnxt.h",
      "insertions": 4,
      "deletions": 0
    },
    {
      "file": "drivers/net/ethernet/broadcom/bnxt/bnxt_ethtool.c",
      "insertions": 32,
      "deletions": 2
    }
  ],
  "total_insertions": 49,
  "total_deletions": 4,
  "total_changes": 53,
  "parents": [
    "1018319f949ced15a66364bddf1fab08ed54817f"
  ],
  "branches": [
    "* development",
    "remotes/origin/HEAD -> origin/master",
    "remotes/origin/master"
  ],
  "tags": [],
  "is_merge": false,
  "security_info": {
    "cve_ids": [],
    "security_keywords": [
      "Authentication"
    ]
  },
  "fix_type": "security",
  "file_results": [
    {
      "file": "drivers/net/ethernet/broadcom/bnxt/bnxt.c",
      "pre_version": true,
      "post_version": true,
      "patch": true
    },
    {
      "file": "drivers/net/ethernet/broadcom/bnxt/bnxt.h",
      "pre_version": true,
      "post_version": true,
      "patch": true
    },
    {
      "file": "drivers/net/ethernet/broadcom/bnxt/bnxt_ethtool.c",
      "pre_version": true,
      "post_version": true,
      "patch": true
    }
  ]
}