{
  "hash": "c9c3a0604614344f7c73523176b6d0a85cba6eab",
  "hash_short": "c9c3a060",
  "subject": "mac80211: verify deauthentication and return error on failure",
  "body": "When still authenticating the mac80211 code handling a deauthentication\nrequests from userspace doesn't verify that the request is valid in any\nway, fix that. Additionally, it never returns an error, even if there's\nno connection or authentication attempt, fix that as well.\n\nWhile at it, move the message to not print a message in the error case\nand to distinguish between the two cases.\n\nAlso simplify the code by duplicating the cfg80211 call.\n\nReviewed-by: Luciano Coelho <luciano.coelho@intel.com>\nSigned-off-by: Johannes Berg <johannes.berg@intel.com>",
  "full_message": "mac80211: verify deauthentication and return error on failure\n\nWhen still authenticating the mac80211 code handling a deauthentication\nrequests from userspace doesn't verify that the request is valid in any\nway, fix that. Additionally, it never returns an error, even if there's\nno connection or authentication attempt, fix that as well.\n\nWhile at it, move the message to not print a message in the error case\nand to distinguish between the two cases.\n\nAlso simplify the code by duplicating the cfg80211 call.\n\nReviewed-by: Luciano Coelho <luciano.coelho@intel.com>\nSigned-off-by: Johannes Berg <johannes.berg@intel.com>",
  "author_name": "Johannes Berg",
  "author_email": "johannes.berg@intel.com",
  "author_date": "Wed Mar 19 09:11:19 2014 +0100",
  "author_date_iso": "2014-03-19T09:11:19+01:00",
  "committer_name": "Johannes Berg",
  "committer_email": "johannes.berg@intel.com",
  "committer_date": "Wed Mar 19 21:29:53 2014 +0100",
  "committer_date_iso": "2014-03-19T21:29:53+01:00",
  "files_changed": [
    "net/mac80211/mlme.c"
  ],
  "files_changed_count": 1,
  "stats": [
    {
      "file": "net/mac80211/mlme.c",
      "insertions": 17,
      "deletions": 13
    }
  ],
  "total_insertions": 17,
  "total_deletions": 13,
  "total_changes": 30,
  "parents": [
    "d2722f8b87fb172ff2f31d3a2816b31d58678d40"
  ],
  "branches": [
    "* development",
    "master",
    "remotes/origin/HEAD -> origin/master",
    "remotes/origin/master"
  ],
  "tags": [
    "v3.15",
    "v3.15-rc1",
    "v3.15-rc2",
    "v3.15-rc3",
    "v3.15-rc4",
    "v3.15-rc5",
    "v3.15-rc6",
    "v3.15-rc7",
    "v3.15-rc8",
    "v3.16"
  ],
  "is_merge": false,
  "security_info": {
    "cve_ids": [],
    "security_keywords": [
      "authentication"
    ]
  },
  "fix_type": "security",
  "file_results": [
    {
      "file": "net/mac80211/mlme.c",
      "pre_version": true,
      "post_version": true,
      "patch": true
    }
  ]
}