{
  "hash": "d70da12453ac3797e0c54884305ccc894e8c817b",
  "hash_short": "d70da124",
  "subject": "hardening: Enable i386 FORTIFY_SOURCE on Clang 16+",
  "body": "The i386 regparm bug exposed with FORTIFY_SOURCE with Clang was fixed\nin Clang 16[1].\n\nLink: https://github.com/llvm/llvm-project/commit/c167c0a4dcdb998affb2756ce76903a12f7d8ca5 [1]\nReviewed-by: Nathan Chancellor <nathan@kernel.org>\nLink: https://lore.kernel.org/r/20250308042929.1753543-2-kees@kernel.org\nSigned-off-by: Kees Cook <kees@kernel.org>",
  "full_message": "hardening: Enable i386 FORTIFY_SOURCE on Clang 16+\n\nThe i386 regparm bug exposed with FORTIFY_SOURCE with Clang was fixed\nin Clang 16[1].\n\nLink: https://github.com/llvm/llvm-project/commit/c167c0a4dcdb998affb2756ce76903a12f7d8ca5 [1]\nReviewed-by: Nathan Chancellor <nathan@kernel.org>\nLink: https://lore.kernel.org/r/20250308042929.1753543-2-kees@kernel.org\nSigned-off-by: Kees Cook <kees@kernel.org>",
  "author_name": "Kees Cook",
  "author_email": "kees@kernel.org",
  "author_date": "Fri Mar 7 20:29:26 2025 -0800",
  "author_date_iso": "2025-03-07T20:29:26-08:00",
  "committer_name": "Kees Cook",
  "committer_email": "kees@kernel.org",
  "committer_date": "Sat Mar 8 09:16:42 2025 -0800",
  "committer_date_iso": "2025-03-08T09:16:42-08:00",
  "files_changed": [
    "arch/x86/Makefile",
    "security/Kconfig.hardening"
  ],
  "files_changed_count": 2,
  "stats": [
    {
      "file": "arch/x86/Makefile",
      "insertions": 1,
      "deletions": 1
    },
    {
      "file": "security/Kconfig.hardening",
      "insertions": 1,
      "deletions": 1
    }
  ],
  "total_insertions": 2,
  "total_deletions": 2,
  "total_changes": 4,
  "parents": [
    "16cb16e0d28501f6eef7071675f1ffbceea8dd0d"
  ],
  "branches": [
    "* development",
    "remotes/origin/HEAD -> origin/master",
    "remotes/origin/master"
  ],
  "tags": [],
  "is_merge": false,
  "security_info": {
    "cve_ids": [],
    "security_keywords": [
      "hardening"
    ]
  },
  "fix_type": "security",
  "file_results": [
    {
      "file": "arch/x86/Makefile",
      "pre_version": true,
      "post_version": true,
      "patch": true
    },
    {
      "file": "security/Kconfig.hardening",
      "pre_version": false,
      "post_version": true,
      "patch": true
    }
  ]
}