{
  "hash": "1f3ef0efbacb2aa63e8e3933664192ee27d0d95b",
  "hash_short": "1f3ef0ef",
  "subject": "drm/amdgpu: add uncorrectable error count print in UMC ecc irq cb",
  "body": "Uncorrectable error count printing is missed when issuing UMC\nUE injection. When going to the error count log function in GPU\nrecover work thread, there is no chance to get correct error count\nvalue by last error injection and print, because the error status\nregister is automatically cleared after reading in UMC ecc irq\ncallback. So add such message printing in UMC ecc irq cb to be\nconsistent with other RAS error interrupt cases.\n\nSigned-off-by: Guchun Chen <guchun.chen@amd.com>\nReviewed-by: Tao Zhou <tao.zhou1@amd.com>\nSigned-off-by: Alex Deucher <alexander.deucher@amd.com>",
  "full_message": "drm/amdgpu: add uncorrectable error count print in UMC ecc irq cb\n\nUncorrectable error count printing is missed when issuing UMC\nUE injection. When going to the error count log function in GPU\nrecover work thread, there is no chance to get correct error count\nvalue by last error injection and print, because the error status\nregister is automatically cleared after reading in UMC ecc irq\ncallback. So add such message printing in UMC ecc irq cb to be\nconsistent with other RAS error interrupt cases.\n\nSigned-off-by: Guchun Chen <guchun.chen@amd.com>\nReviewed-by: Tao Zhou <tao.zhou1@amd.com>\nSigned-off-by: Alex Deucher <alexander.deucher@amd.com>",
  "author_name": "Guchun Chen",
  "author_email": "guchun.chen@amd.com",
  "author_date": "Fri Apr 10 11:41:54 2020 +0800",
  "author_date_iso": "2020-04-10T11:41:54+08:00",
  "committer_name": "Alex Deucher",
  "committer_email": "alexander.deucher@amd.com",
  "committer_date": "Mon Apr 13 12:01:44 2020 -0400",
  "committer_date_iso": "2020-04-13T12:01:44-04:00",
  "files_changed": [
    "drivers/gpu/drm/amd/amdgpu/amdgpu_umc.c"
  ],
  "files_changed_count": 1,
  "stats": [
    {
      "file": "drivers/gpu/drm/amd/amdgpu/amdgpu_umc.c",
      "insertions": 3,
      "deletions": 0
    }
  ],
  "total_insertions": 3,
  "total_deletions": 0,
  "total_changes": 3,
  "parents": [
    "7adf5619ae82244446e0e9e5199d96c316f3c80d"
  ],
  "branches": [
    "* development",
    "remotes/origin/HEAD -> origin/master",
    "remotes/origin/master"
  ],
  "tags": [],
  "is_merge": false,
  "security_info": {
    "cve_ids": [],
    "security_keywords": [
      "injection"
    ]
  },
  "fix_type": "security",
  "file_results": [
    {
      "file": "drivers/gpu/drm/amd/amdgpu/amdgpu_umc.c",
      "pre_version": false,
      "post_version": true,
      "patch": true
    }
  ]
}