{
  "hash": "3aef021b2df7d8440225a53460c0d34b140297d5",
  "hash_short": "3aef021b",
  "subject": "mei: limit number of bytes in mei header.",
  "body": "The MEI message header provides only 9 bits for storing\nthe message size, limiting to 511.\nIn theory the host buffer (hbuf) can contain up to 1020 bytes\n(limited by byte =  255 * 4)\nWith the current hardware and hbuf size 512, this is not a real issue,\nbut as hardening approach we enforce the limit.\n\nSigned-off-by: Tomas Winkler <tomas.winkler@intel.com>\nLink: https://lore.kernel.org/r/20200211160522.7562-1-tomas.winkler@intel.com\nSigned-off-by: Greg Kroah-Hartman <gregkh@linuxfoundation.org>",
  "full_message": "mei: limit number of bytes in mei header.\n\nThe MEI message header provides only 9 bits for storing\nthe message size, limiting to 511.\nIn theory the host buffer (hbuf) can contain up to 1020 bytes\n(limited by byte =  255 * 4)\nWith the current hardware and hbuf size 512, this is not a real issue,\nbut as hardening approach we enforce the limit.\n\nSigned-off-by: Tomas Winkler <tomas.winkler@intel.com>\nLink: https://lore.kernel.org/r/20200211160522.7562-1-tomas.winkler@intel.com\nSigned-off-by: Greg Kroah-Hartman <gregkh@linuxfoundation.org>",
  "author_name": "Tomas Winkler",
  "author_email": "tomas.winkler@intel.com",
  "author_date": "Tue Feb 11 18:05:22 2020 +0200",
  "author_date_iso": "2020-02-11T18:05:22+02:00",
  "committer_name": "Greg Kroah-Hartman",
  "committer_email": "gregkh@linuxfoundation.org",
  "committer_date": "Tue Feb 11 14:03:19 2020 -0800",
  "committer_date_iso": "2020-02-11T14:03:19-08:00",
  "files_changed": [
    "drivers/misc/mei/client.c",
    "drivers/misc/mei/hw.h"
  ],
  "files_changed_count": 2,
  "stats": [
    {
      "file": "drivers/misc/mei/client.c",
      "insertions": 2,
      "deletions": 2
    },
    {
      "file": "drivers/misc/mei/hw.h",
      "insertions": 3,
      "deletions": 0
    }
  ],
  "total_insertions": 5,
  "total_deletions": 2,
  "total_changes": 7,
  "parents": [
    "6736041f9606f195339cacb4bcce232f1a2a1ed3"
  ],
  "branches": [
    "* development",
    "master",
    "remotes/origin/HEAD -> origin/master",
    "remotes/origin/master"
  ],
  "tags": [
    "v5.7-rc1"
  ],
  "is_merge": false,
  "security_info": {
    "cve_ids": [],
    "security_keywords": [
      "hardening"
    ]
  },
  "fix_type": "security",
  "file_results": [
    {
      "file": "drivers/misc/mei/client.c",
      "pre_version": false,
      "post_version": true,
      "patch": true
    },
    {
      "file": "drivers/misc/mei/hw.h",
      "pre_version": false,
      "post_version": true,
      "patch": true
    }
  ]
}