{
  "hash": "f8acb24aaf89fc46cd953229462ea8abe31b395f",
  "hash_short": "f8acb24a",
  "subject": "x86/hyperv: Block root partition functionality in a Confidential VM",
  "body": "Hyper-V should never specify a VM that is a Confidential VM and also\nrunning in the root partition.  Nonetheless, explicitly block such a\ncombination to guard against a compromised Hyper-V maliciously trying to\nexploit root partition functionality in a Confidential VM to expose\nConfidential VM secrets. No known bug is being fixed, but the attack\nsurface for Confidential VMs on Hyper-V is reduced.\n\nSigned-off-by: Michael Kelley <mikelley@microsoft.com>\nLink: https://lore.kernel.org/r/1678894453-95392-1-git-send-email-mikelley@microsoft.com\nSigned-off-by: Wei Liu <wei.liu@kernel.org>",
  "full_message": "x86/hyperv: Block root partition functionality in a Confidential VM\n\nHyper-V should never specify a VM that is a Confidential VM and also\nrunning in the root partition.  Nonetheless, explicitly block such a\ncombination to guard against a compromised Hyper-V maliciously trying to\nexploit root partition functionality in a Confidential VM to expose\nConfidential VM secrets. No known bug is being fixed, but the attack\nsurface for Confidential VMs on Hyper-V is reduced.\n\nSigned-off-by: Michael Kelley <mikelley@microsoft.com>\nLink: https://lore.kernel.org/r/1678894453-95392-1-git-send-email-mikelley@microsoft.com\nSigned-off-by: Wei Liu <wei.liu@kernel.org>",
  "author_name": "Michael Kelley",
  "author_email": "mikelley@microsoft.com",
  "author_date": "Wed Mar 15 08:34:13 2023 -0700",
  "author_date_iso": "2023-03-15T08:34:13-07:00",
  "committer_name": "Wei Liu",
  "committer_email": "wei.liu@kernel.org",
  "committer_date": "Fri Mar 17 10:57:35 2023 +0000",
  "committer_date_iso": "2023-03-17T10:57:35+00:00",
  "files_changed": [
    "arch/x86/kernel/cpu/mshyperv.c"
  ],
  "files_changed_count": 1,
  "stats": [
    {
      "file": "arch/x86/kernel/cpu/mshyperv.c",
      "insertions": 8,
      "deletions": 4
    }
  ],
  "total_insertions": 8,
  "total_deletions": 4,
  "total_changes": 12,
  "parents": [
    "1eb65c8687316c65140b48fad27133d583178e15"
  ],
  "branches": [
    "* development",
    "remotes/origin/HEAD -> origin/master",
    "remotes/origin/master"
  ],
  "tags": [],
  "is_merge": false,
  "security_info": {
    "cve_ids": [],
    "security_keywords": [
      "exploit"
    ]
  },
  "fix_type": "security",
  "file_results": [
    {
      "file": "arch/x86/kernel/cpu/mshyperv.c",
      "pre_version": false,
      "post_version": true,
      "patch": true
    }
  ]
}