{
  "hash": "0f34802858e74e708c6d42209811f6d264892c8f",
  "hash_short": "0f348028",
  "subject": "f2fs: support checkpoint error injection",
  "body": "This patch adds to support checkpoint error injection in f2fs for testing\nfatal error tolerance, it will be useful that it can simulate abnormal\npower off by f2fs itself instead of calling godown ioctl by running apps.\n\nSigned-off-by: Chao Yu <yuchao0@huawei.com>\nSigned-off-by: Jaegeuk Kim <jaegeuk@kernel.org>",
  "full_message": "f2fs: support checkpoint error injection\n\nThis patch adds to support checkpoint error injection in f2fs for testing\nfatal error tolerance, it will be useful that it can simulate abnormal\npower off by f2fs itself instead of calling godown ioctl by running apps.\n\nSigned-off-by: Chao Yu <yuchao0@huawei.com>\nSigned-off-by: Jaegeuk Kim <jaegeuk@kernel.org>",
  "author_name": "Chao Yu",
  "author_email": "yuchao0@huawei.com",
  "author_date": "Mon Sep 26 19:45:55 2016 +0800",
  "author_date_iso": "2016-09-26T19:45:55+08:00",
  "committer_name": "Jaegeuk Kim",
  "committer_email": "jaegeuk@kernel.org",
  "committer_date": "Fri Sep 30 17:34:35 2016 -0700",
  "committer_date_iso": "2016-09-30T17:34:35-07:00",
  "files_changed": [
    "fs/f2fs/f2fs.h",
    "fs/f2fs/gc.c",
    "fs/f2fs/segment.c",
    "fs/f2fs/super.c"
  ],
  "files_changed_count": 4,
  "stats": [
    {
      "file": "fs/f2fs/f2fs.h",
      "insertions": 1,
      "deletions": 0
    },
    {
      "file": "fs/f2fs/gc.c",
      "insertions": 5,
      "deletions": 0
    },
    {
      "file": "fs/f2fs/segment.c",
      "insertions": 5,
      "deletions": 0
    },
    {
      "file": "fs/f2fs/super.c",
      "insertions": 1,
      "deletions": 0
    }
  ],
  "total_insertions": 12,
  "total_deletions": 0,
  "total_changes": 12,
  "parents": [
    "2443b8b363917468e2fb163b34c8f14fe1546251"
  ],
  "branches": [
    "* development",
    "master",
    "remotes/origin/HEAD -> origin/master",
    "remotes/origin/master"
  ],
  "tags": [
    "v4.10",
    "v4.10-rc1",
    "v4.10-rc2",
    "v4.10-rc3",
    "v4.10-rc4",
    "v4.10-rc5",
    "v4.10-rc6",
    "v4.10-rc7",
    "v4.10-rc8",
    "v4.11"
  ],
  "is_merge": false,
  "security_info": {
    "cve_ids": [],
    "security_keywords": [
      "injection"
    ]
  },
  "fix_type": "security",
  "file_results": [
    {
      "file": "fs/f2fs/f2fs.h",
      "pre_version": false,
      "post_version": true,
      "patch": true
    },
    {
      "file": "fs/f2fs/gc.c",
      "pre_version": false,
      "post_version": true,
      "patch": true
    },
    {
      "file": "fs/f2fs/segment.c",
      "pre_version": false,
      "post_version": true,
      "patch": true
    },
    {
      "file": "fs/f2fs/super.c",
      "pre_version": true,
      "post_version": true,
      "patch": true
    }
  ]
}