{
  "hash": "6f4219dd7df0b834caad344db05d9d06d71658cd",
  "hash_short": "6f4219dd",
  "subject": "greybus: Documentation: Document Authentication interfaces",
  "body": "This patch defined userspace interface of the CAP protocol.\n\nSigned-off-by: Viresh Kumar <viresh.kumar@linaro.org>\nReviewed-by: Jun Li <li_jun@projectara.com>\nTested-by: Jun Li <li_jun@projectara.com>\nSigned-off-by: Alex Elder <elder@linaro.org>",
  "full_message": "greybus: Documentation: Document Authentication interfaces\n\nThis patch defined userspace interface of the CAP protocol.\n\nSigned-off-by: Viresh Kumar <viresh.kumar@linaro.org>\nReviewed-by: Jun Li <li_jun@projectara.com>\nTested-by: Jun Li <li_jun@projectara.com>\nSigned-off-by: Alex Elder <elder@linaro.org>",
  "author_name": "Viresh Kumar",
  "author_email": "viresh.kumar@linaro.org",
  "author_date": "Thu Jun 30 10:54:00 2016 -0500",
  "author_date_iso": "2016-06-30T10:54:00-05:00",
  "committer_name": "Alex Elder",
  "committer_email": "elder@linaro.org",
  "committer_date": "Wed Jul 6 17:51:32 2016 -0500",
  "committer_date_iso": "2016-07-06T17:51:32-05:00",
  "files_changed": [
    "drivers/staging/greybus/Documentation/firmware/authenticate.c",
    "drivers/staging/greybus/Documentation/firmware/firmware-management"
  ],
  "files_changed_count": 2,
  "stats": [
    {
      "file": "drivers/staging/greybus/Documentation/firmware/authenticate.c",
      "insertions": 139,
      "deletions": 0
    },
    {
      "file": "drivers/staging/greybus/Documentation/firmware/firmware-management",
      "insertions": 130,
      "deletions": 4
    }
  ],
  "total_insertions": 269,
  "total_deletions": 4,
  "total_changes": 273,
  "parents": [
    "e3eda54d0b5fef23957cc4f586f4b44fd223c881"
  ],
  "branches": [
    "* development",
    "master",
    "remotes/origin/HEAD -> origin/master",
    "remotes/origin/master"
  ],
  "tags": [
    "v4.10",
    "v4.10-rc1",
    "v4.10-rc2",
    "v4.10-rc3",
    "v4.10-rc4",
    "v4.10-rc5",
    "v4.10-rc6",
    "v4.10-rc7",
    "v4.10-rc8",
    "v4.11"
  ],
  "is_merge": false,
  "security_info": {
    "cve_ids": [],
    "security_keywords": [
      "Authentication"
    ]
  },
  "fix_type": "security",
  "file_results": [
    {
      "file": "drivers/staging/greybus/Documentation/firmware/authenticate.c",
      "pre_version": false,
      "post_version": true,
      "patch": true
    },
    {
      "file": "drivers/staging/greybus/Documentation/firmware/firmware-management",
      "pre_version": false,
      "post_version": true,
      "patch": true
    }
  ]
}