{
  "hash": "4c282e51e4450b94680d6ca3b10f830483b1f243",
  "hash_short": "4c282e51",
  "subject": "KVM: x86: Update vCPU's runtime CPUID on write to MSR_IA32_XSS",
  "body": "Do a runtime CPUID update for a vCPU if MSR_IA32_XSS is written, as the\nsize in bytes of the XSAVE area is affected by the states enabled in XSS.\n\nFixes: 203000993de5 (\"kvm: vmx: add MSR logic for XSAVES\")\nCc: stable@vger.kernel.org\nSigned-off-by: Like Xu <likexu@tencent.com>\n[sean: split out as a separate patch, adjust Fixes tag]\nSigned-off-by: Sean Christopherson <seanjc@google.com>\nMessage-Id: <20220126172226.2298529-3-seanjc@google.com>\nSigned-off-by: Paolo Bonzini <pbonzini@redhat.com>",
  "full_message": "KVM: x86: Update vCPU's runtime CPUID on write to MSR_IA32_XSS\n\nDo a runtime CPUID update for a vCPU if MSR_IA32_XSS is written, as the\nsize in bytes of the XSAVE area is affected by the states enabled in XSS.\n\nFixes: 203000993de5 (\"kvm: vmx: add MSR logic for XSAVES\")\nCc: stable@vger.kernel.org\nSigned-off-by: Like Xu <likexu@tencent.com>\n[sean: split out as a separate patch, adjust Fixes tag]\nSigned-off-by: Sean Christopherson <seanjc@google.com>\nMessage-Id: <20220126172226.2298529-3-seanjc@google.com>\nSigned-off-by: Paolo Bonzini <pbonzini@redhat.com>",
  "author_name": "Like Xu",
  "author_email": "likexu@tencent.com",
  "author_date": "Wed Jan 26 17:22:25 2022 +0000",
  "author_date_iso": "2022-01-26T17:22:25+00:00",
  "committer_name": "Paolo Bonzini",
  "committer_email": "pbonzini@redhat.com",
  "committer_date": "Wed Jan 26 12:42:45 2022 -0500",
  "committer_date_iso": "2022-01-26T12:42:45-05:00",
  "files_changed": [
    "arch/x86/kvm/x86.c"
  ],
  "files_changed_count": 1,
  "stats": [
    {
      "file": "arch/x86/kvm/x86.c",
      "insertions": 1,
      "deletions": 0
    }
  ],
  "total_insertions": 1,
  "total_deletions": 0,
  "total_changes": 1,
  "parents": [
    "be4f3b3f82271c3193ce200a996dc70682c8e622"
  ],
  "branches": [
    "* development",
    "remotes/origin/HEAD -> origin/master",
    "remotes/origin/master"
  ],
  "tags": [],
  "is_merge": false,
  "security_info": {
    "cve_ids": [],
    "security_keywords": [
      "XSS"
    ]
  },
  "fix_type": "security",
  "file_results": [
    {
      "file": "arch/x86/kvm/x86.c",
      "pre_version": true,
      "post_version": true,
      "patch": true
    }
  ]
}