{
  "hash": "f89b23217372ed9bdba8804c1616d445402d1e05",
  "hash_short": "f89b2321",
  "subject": "[PATCH] airo.c: add support for IW_ENCODE_TEMP (i.e. xsupplicant)",
  "body": "Hello Jeff,\n\nthis patch changes causes the airo driver to not reset the card when a\ntemporary WEP key is set, when the IW_ENCODE_TEMP flag is used.  This is\nneeded for xsupplicant as 802.1x, LEAP, etc. change WEP keys frequently\nafter authentication and resetting the card causes infinite\nreauthentication.\n\nJavier and Jean agree with the patch, Javier suggested I send this to\nyou, can you apply this?\n\nThanks.\n\nSigned-off-by: Dan Streetman <ddstreet@ieee.org>\nSigned-off-by: Jeff Garzik <jgarzik@pobox.com>",
  "full_message": "[PATCH] airo.c: add support for IW_ENCODE_TEMP (i.e. xsupplicant)\n\nHello Jeff,\n\nthis patch changes causes the airo driver to not reset the card when a\ntemporary WEP key is set, when the IW_ENCODE_TEMP flag is used.  This is\nneeded for xsupplicant as 802.1x, LEAP, etc. change WEP keys frequently\nafter authentication and resetting the card causes infinite\nreauthentication.\n\nJavier and Jean agree with the patch, Javier suggested I send this to\nyou, can you apply this?\n\nThanks.\n\nSigned-off-by: Dan Streetman <ddstreet@ieee.org>\nSigned-off-by: Jeff Garzik <jgarzik@pobox.com>",
  "author_name": "Dan Streetman",
  "author_email": "ddstreet@ieee.org",
  "author_date": "Fri Nov 11 11:41:42 2005 -0500",
  "author_date_iso": "2005-11-11T11:41:42-05:00",
  "committer_name": "Jeff Garzik",
  "committer_email": "jgarzik@pobox.com",
  "committer_date": "Thu Dec 1 02:40:34 2005 -0500",
  "committer_date_iso": "2005-12-01T02:40:34-05:00",
  "files_changed": [
    "drivers/net/wireless/airo.c"
  ],
  "files_changed_count": 1,
  "stats": [
    {
      "file": "drivers/net/wireless/airo.c",
      "insertions": 8,
      "deletions": 7
    }
  ],
  "total_insertions": 8,
  "total_deletions": 7,
  "total_changes": 15,
  "parents": [
    "127477840b9fd205958203648b9fa89860d69a43"
  ],
  "branches": [
    "* development",
    "master",
    "remotes/origin/HEAD -> origin/master",
    "remotes/origin/master"
  ],
  "tags": [
    "v2.6.16",
    "v2.6.16-rc1",
    "v2.6.16-rc2",
    "v2.6.16-rc3",
    "v2.6.16-rc4",
    "v2.6.16-rc5",
    "v2.6.16-rc6",
    "v2.6.17",
    "v2.6.17-rc1",
    "v2.6.17-rc2"
  ],
  "is_merge": false,
  "security_info": {
    "cve_ids": [],
    "security_keywords": [
      "authentication"
    ]
  },
  "fix_type": "security",
  "file_results": [
    {
      "file": "drivers/net/wireless/airo.c",
      "pre_version": false,
      "post_version": true,
      "patch": true
    }
  ]
}