{
  "hash": "1fd8de46d01d95f875c12684a6a03559831e8b4c",
  "hash_short": "1fd8de46",
  "subject": "x86/jump_label: Use text_poke_early() during early init",
  "body": "There is no apparent reason not to use text_poke_early() during\nearly-init, since no patching of code that might be on the stack is done\nand only a single core is running.\n\nThis is required for the next patches that would set a temporary mm for\ntext poking, and this mm is only initialized after some static-keys are\nenabled/disabled.\n\nSigned-off-by: Nadav Amit <namit@vmware.com>\nSigned-off-by: Rick Edgecombe <rick.p.edgecombe@intel.com>\nSigned-off-by: Peter Zijlstra (Intel) <peterz@infradead.org>\nCc: <akpm@linux-foundation.org>\nCc: <ard.biesheuvel@linaro.org>\nCc: <deneen.t.dock@intel.com>\nCc: <kernel-hardening@lists.openwall.com>\nCc: <kristen@linux.intel.com>\nCc: <linux_dti@icloud.com>\nCc: <will.deacon@arm.com>\nCc: Andy Lutomirski <luto@kernel.org>\nCc: Borislav Petkov <bp@alien8.de>\nCc: Dave Hansen <dave.hansen@intel.com>\nCc: H. Peter Anvin <hpa@zytor.com>\nCc: Kees Cook <keescook@chromium.org>\nCc: Linus Torvalds <torvalds@linux-foundation.org>\nCc: Masami Hiramatsu <mhiramat@kernel.org>\nCc: Rik van Riel <riel@surriel.com>\nCc: Thomas Gleixner <tglx@linutronix.de>\nLink: https://lkml.kernel.org/r/20190426001143.4983-3-namit@vmware.com\nSigned-off-by: Ingo Molnar <mingo@kernel.org>",
  "full_message": "x86/jump_label: Use text_poke_early() during early init\n\nThere is no apparent reason not to use text_poke_early() during\nearly-init, since no patching of code that might be on the stack is done\nand only a single core is running.\n\nThis is required for the next patches that would set a temporary mm for\ntext poking, and this mm is only initialized after some static-keys are\nenabled/disabled.\n\nSigned-off-by: Nadav Amit <namit@vmware.com>\nSigned-off-by: Rick Edgecombe <rick.p.edgecombe@intel.com>\nSigned-off-by: Peter Zijlstra (Intel) <peterz@infradead.org>\nCc: <akpm@linux-foundation.org>\nCc: <ard.biesheuvel@linaro.org>\nCc: <deneen.t.dock@intel.com>\nCc: <kernel-hardening@lists.openwall.com>\nCc: <kristen@linux.intel.com>\nCc: <linux_dti@icloud.com>\nCc: <will.deacon@arm.com>\nCc: Andy Lutomirski <luto@kernel.org>\nCc: Borislav Petkov <bp@alien8.de>\nCc: Dave Hansen <dave.hansen@intel.com>\nCc: H. Peter Anvin <hpa@zytor.com>\nCc: Kees Cook <keescook@chromium.org>\nCc: Linus Torvalds <torvalds@linux-foundation.org>\nCc: Masami Hiramatsu <mhiramat@kernel.org>\nCc: Rik van Riel <riel@surriel.com>\nCc: Thomas Gleixner <tglx@linutronix.de>\nLink: https://lkml.kernel.org/r/20190426001143.4983-3-namit@vmware.com\nSigned-off-by: Ingo Molnar <mingo@kernel.org>",
  "author_name": "Nadav Amit",
  "author_email": "namit@vmware.com",
  "author_date": "Thu Apr 25 17:11:22 2019 -0700",
  "author_date_iso": "2019-04-25T17:11:22-07:00",
  "committer_name": "Ingo Molnar",
  "committer_email": "mingo@kernel.org",
  "committer_date": "Tue Apr 30 12:37:49 2019 +0200",
  "committer_date_iso": "2019-04-30T12:37:49+02:00",
  "files_changed": [
    "arch/x86/kernel/jump_label.c"
  ],
  "files_changed_count": 1,
  "stats": [
    {
      "file": "arch/x86/kernel/jump_label.c",
      "insertions": 6,
      "deletions": 1
    }
  ],
  "total_insertions": 6,
  "total_deletions": 1,
  "total_changes": 7,
  "parents": [
    "c7b6f29b6257532792fc722b68fcc0e00b5a856c"
  ],
  "branches": [
    "* development",
    "master",
    "remotes/origin/HEAD -> origin/master",
    "remotes/origin/master"
  ],
  "tags": [
    "v5.2",
    "v5.2-rc1",
    "v5.2-rc2",
    "v5.2-rc3",
    "v5.2-rc4",
    "v5.2-rc5",
    "v5.2-rc6",
    "v5.2-rc7",
    "v5.3",
    "v5.3-rc1"
  ],
  "is_merge": false,
  "security_info": {
    "cve_ids": [],
    "security_keywords": [
      "hardening"
    ]
  },
  "fix_type": "security",
  "file_results": [
    {
      "file": "arch/x86/kernel/jump_label.c",
      "pre_version": false,
      "post_version": true,
      "patch": true
    }
  ]
}