{
  "hash": "f1b4bd0676c2b3d4a023cf3f5d535e618f7e6eff",
  "hash_short": "f1b4bd06",
  "subject": "fault-injection: reorder config entries",
  "body": "Reorder Kconfig entries, so that menuconfig displays proper indentation.\n\nLink: http://lkml.kernel.org/r/alpine.LRH.2.02.1804251601160.30569@file01.intranet.prod.int.rdu2.redhat.com\nSigned-off-by: Mikulas Patocka <mpatocka@redhat.com>\nAcked-by: Randy Dunlap <rdunlap@infradead.org>\nTested-by: Randy Dunlap <rdunlap@infradead.org>\nSigned-off-by: Andrew Morton <akpm@linux-foundation.org>\nSigned-off-by: Linus Torvalds <torvalds@linux-foundation.org>",
  "full_message": "fault-injection: reorder config entries\n\nReorder Kconfig entries, so that menuconfig displays proper indentation.\n\nLink: http://lkml.kernel.org/r/alpine.LRH.2.02.1804251601160.30569@file01.intranet.prod.int.rdu2.redhat.com\nSigned-off-by: Mikulas Patocka <mpatocka@redhat.com>\nAcked-by: Randy Dunlap <rdunlap@infradead.org>\nTested-by: Randy Dunlap <rdunlap@infradead.org>\nSigned-off-by: Andrew Morton <akpm@linux-foundation.org>\nSigned-off-by: Linus Torvalds <torvalds@linux-foundation.org>",
  "author_name": "Mikulas Patocka",
  "author_email": "mpatocka@redhat.com",
  "author_date": "Thu Jun 14 15:27:48 2018 -0700",
  "author_date_iso": "2018-06-14T15:27:48-07:00",
  "committer_name": "Linus Torvalds",
  "committer_email": "torvalds@linux-foundation.org",
  "committer_date": "Fri Jun 15 07:55:24 2018 +0900",
  "committer_date_iso": "2018-06-15T07:55:24+09:00",
  "files_changed": [
    "lib/Kconfig.debug"
  ],
  "files_changed_count": 1,
  "stats": [
    {
      "file": "lib/Kconfig.debug",
      "insertions": 18,
      "deletions": 18
    }
  ],
  "total_insertions": 18,
  "total_deletions": 18,
  "total_changes": 36,
  "parents": [
    "758517202bd2e427664857c9f2aa59da36848aca"
  ],
  "branches": [
    "* development",
    "master",
    "remotes/origin/HEAD -> origin/master",
    "remotes/origin/master"
  ],
  "tags": [
    "v4.18",
    "v4.18-rc1",
    "v4.18-rc2",
    "v4.18-rc3",
    "v4.18-rc4",
    "v4.18-rc5",
    "v4.18-rc6",
    "v4.18-rc7",
    "v4.18-rc8",
    "v4.19"
  ],
  "is_merge": false,
  "security_info": {
    "cve_ids": [],
    "security_keywords": [
      "injection"
    ]
  },
  "fix_type": "security",
  "file_results": [
    {
      "file": "lib/Kconfig.debug",
      "pre_version": false,
      "post_version": true,
      "patch": true
    }
  ]
}