{
  "hash": "a19944809fe9942e6a96292490717904d0690c21",
  "hash_short": "a1994480",
  "subject": "Merge tag 'hardening-v5.18-rc3' of git://git.kernel.org/pub/scm/linux/kernel/git/kees/linux",
  "body": "Pull hardening fixes from Kees Cook:\n\n - latent_entropy: Use /dev/urandom instead of small GCC seed (Jason\n   Donenfeld)\n\n - uapi/stddef.h: add missed include guards (Tadeusz Struk)\n\n* tag 'hardening-v5.18-rc3' of git://git.kernel.org/pub/scm/linux/kernel/git/kees/linux:\n  gcc-plugins: latent_entropy: use /dev/urandom\n  uapi/linux/stddef.h: Add include guards",
  "full_message": "Merge tag 'hardening-v5.18-rc3' of git://git.kernel.org/pub/scm/linux/kernel/git/kees/linux\n\nPull hardening fixes from Kees Cook:\n\n - latent_entropy: Use /dev/urandom instead of small GCC seed (Jason\n   Donenfeld)\n\n - uapi/stddef.h: add missed include guards (Tadeusz Struk)\n\n* tag 'hardening-v5.18-rc3' of git://git.kernel.org/pub/scm/linux/kernel/git/kees/linux:\n  gcc-plugins: latent_entropy: use /dev/urandom\n  uapi/linux/stddef.h: Add include guards",
  "author_name": "Linus Torvalds",
  "author_email": "torvalds@linux-foundation.org",
  "author_date": "Tue Apr 12 14:29:40 2022 -1000",
  "author_date_iso": "2022-04-12T14:29:40-10:00",
  "committer_name": "Linus Torvalds",
  "committer_email": "torvalds@linux-foundation.org",
  "committer_date": "Tue Apr 12 14:29:40 2022 -1000",
  "committer_date_iso": "2022-04-12T14:29:40-10:00",
  "files_changed": [],
  "files_changed_count": 0,
  "stats": [
    {
      "file": "include/uapi/linux/stddef.h",
      "insertions": 4,
      "deletions": 0
    },
    {
      "file": "scripts/gcc-plugins/latent_entropy_plugin.c",
      "insertions": 27,
      "deletions": 17
    }
  ],
  "total_insertions": 31,
  "total_deletions": 17,
  "total_changes": 48,
  "parents": [
    "c1488c97517adab67087aa7ed43658af49dbd0ab",
    "c40160f2998c897231f8454bf797558d30a20375"
  ],
  "branches": [
    "* development",
    "remotes/origin/HEAD -> origin/master",
    "remotes/origin/master"
  ],
  "tags": [],
  "is_merge": true,
  "security_info": {
    "cve_ids": [],
    "security_keywords": [
      "hardening"
    ]
  },
  "fix_type": "security",
  "file_results": []
}