{
  "hash": "38e29671813bef415288fd42f378f703f185aa55",
  "hash_short": "38e29671",
  "subject": "arm64/sysreg: Align pointer auth enumeration defines with architecture",
  "body": "The defines used for the pointer authentication feature enumerations do not\nfollow the naming convention we've decided to use where we name things\nafter the architecture feature that introduced. Prepare for generating the\ndefines for the ISA ID registers by updating to use the feature names.\nNo functional changes.\n\nSigned-off-by: Mark Brown <broonie@kernel.org>\nLink: https://lore.kernel.org/r/20220704170302.2609529-10-broonie@kernel.org\nSigned-off-by: Will Deacon <will@kernel.org>",
  "full_message": "arm64/sysreg: Align pointer auth enumeration defines with architecture\n\nThe defines used for the pointer authentication feature enumerations do not\nfollow the naming convention we've decided to use where we name things\nafter the architecture feature that introduced. Prepare for generating the\ndefines for the ISA ID registers by updating to use the feature names.\nNo functional changes.\n\nSigned-off-by: Mark Brown <broonie@kernel.org>\nLink: https://lore.kernel.org/r/20220704170302.2609529-10-broonie@kernel.org\nSigned-off-by: Will Deacon <will@kernel.org>",
  "author_name": "Mark Brown",
  "author_email": "broonie@kernel.org",
  "author_date": "Mon Jul 4 18:02:43 2022 +0100",
  "author_date_iso": "2022-07-04T18:02:43+01:00",
  "committer_name": "Will Deacon",
  "committer_email": "will@kernel.org",
  "committer_date": "Tue Jul 5 11:45:46 2022 +0100",
  "committer_date_iso": "2022-07-05T11:45:46+01:00",
  "files_changed": [
    "arch/arm64/include/asm/sysreg.h",
    "arch/arm64/kernel/cpufeature.c"
  ],
  "files_changed_count": 2,
  "stats": [
    {
      "file": "arch/arm64/include/asm/sysreg.h",
      "insertions": 17,
      "deletions": 17
    },
    {
      "file": "arch/arm64/kernel/cpufeature.c",
      "insertions": 12,
      "deletions": 12
    }
  ],
  "total_insertions": 29,
  "total_deletions": 29,
  "total_changes": 58,
  "parents": [
    "e97575533a801bc9b0c690bb7e58f126ede4ad41"
  ],
  "branches": [
    "* development",
    "remotes/origin/HEAD -> origin/master",
    "remotes/origin/master"
  ],
  "tags": [],
  "is_merge": false,
  "security_info": {
    "cve_ids": [],
    "security_keywords": [
      "auth"
    ]
  },
  "fix_type": "security",
  "file_results": [
    {
      "file": "arch/arm64/include/asm/sysreg.h",
      "pre_version": true,
      "post_version": true,
      "patch": true
    },
    {
      "file": "arch/arm64/kernel/cpufeature.c",
      "pre_version": true,
      "post_version": true,
      "patch": true
    }
  ]
}